matrix3/__init__.py
matrix3/cool_matrix.py
matrix3/matrix.py
matrix_py3-0.0.4.dist-info/LICENSE
matrix_py3-0.0.4.dist-info/METADATA
matrix_py3-0.0.4.dist-info/WHEEL
matrix_py3-0.0.4.dist-info/entry_points.txt
matrix_py3-0.0.4.dist-info/top_level.txt
matrix_py3-0.0.4.dist-info/RECORD
