Metadata-Version: 2.1
Name: matrix-py3
Version: 0.0.4
Summary: Python3 implementation of cmatrix with a timer
Home-page: https://github.com/chunribu/matrix-py3
Author: chunribu
Author-email: chunribu@mail.sdu.edu.cn
License: MIT
Keywords: cmatrix python3 timer
Platform: UNKNOWN
Classifier: Operating System :: POSIX :: Linux
Classifier: Operating System :: MacOS :: MacOS X
Classifier: License :: OSI Approved :: MIT License
Classifier: Programming Language :: Python :: 3
License-File: LICENSE
Requires-Dist: pebble
